lowcarb/__init__.py
lowcarb/_client_manager.py
lowcarb/_strategy.py
flwr_lowcarb-0.1.1.dist-info/LICENSE
flwr_lowcarb-0.1.1.dist-info/METADATA
flwr_lowcarb-0.1.1.dist-info/WHEEL
flwr_lowcarb-0.1.1.dist-info/top_level.txt
flwr_lowcarb-0.1.1.dist-info/RECORD
