Metadata-Version: 2.1
Name: flwr-lowcarb
Version: 0.1.1
Summary: Carbon-aware client selection strategy for Flower
Home-page: https://github.com/birnbaum/lowcarb
Author: Philipp Wiesner, Martin Schellenberger, Dennis Grinwald
Author-email: wiesner@tu-berlin.de
License: MIT
Keywords: carbon awareness,federated learning,client selection,flower
Classifier: Development Status :: 3 - Alpha
Classifier: License :: OSI Approved :: MIT License
Classifier: Operating System :: OS Independent
Classifier: Programming Language :: Python
Classifier: Programming Language :: Python :: 3
Classifier: Programming Language :: Python :: 3.7
Classifier: Programming Language :: Python :: 3.8
Classifier: Programming Language :: Python :: 3.9
Classifier: Programming Language :: Python :: 3.10
Classifier: Programming Language :: Python :: 3.11
Requires-Python: >=3.7
License-File: LICENSE
Requires-Dist: flower
Requires-Dist: numpy
Requires-Dist: pandas
Requires-Dist: urllib3 (>=1.25.3)
Requires-Dist: python-dateutil
